string_repetition/__init__.py
string_repetition/__main__.py
string_repetition/core.py
string_repetition-0.3.2.dist-info/METADATA
string_repetition-0.3.2.dist-info/WHEEL
string_repetition-0.3.2.dist-info/top_level.txt
string_repetition-0.3.2.dist-info/RECORD
