Metadata-Version: 2.1
Name: string-repetition
Version: 0.3.2
Summary: 一个高效的字符串重复检测算法
Author: AdAstraAbyssoque
Author-email: bliu699@outlook.com
Classifier: Programming Language :: Python :: 3
Classifier: License :: OSI Approved :: MIT License
Classifier: Operating System :: OS Independent
Requires-Python: >=3.6
